mlclient/__init__.py
mlclient/__main__.py
mlclient/calls/__init__.py
mlclient/calls/database_call.py
mlclient/calls/database_properties_call.py
mlclient/calls/databases_call.py
mlclient/calls/documents_call.py
mlclient/calls/eval_call.py
mlclient/calls/forest_call.py
mlclient/calls/forest_properties_call.py
mlclient/calls/forests_call.py
mlclient/calls/logs_call.py
mlclient/calls/model/__init__.py
mlclient/calls/model/documents.py
mlclient/calls/resource_call.py
mlclient/calls/role_call.py
mlclient/calls/role_properties_call.py
mlclient/calls/roles_call.py
mlclient/calls/server_call.py
mlclient/calls/server_properties_call.py
mlclient/calls/servers_call.py
mlclient/calls/user_call.py
mlclient/calls/user_properties_call.py
mlclient/calls/users_call.py
mlclient/cli/__init__.py
mlclient/cli/app.py
mlclient/cli/commands/__init__.py
mlclient/cli/commands/call_eval.py
mlclient/cli/commands/call_logs.py
mlclient/clients/__init__.py
mlclient/clients/documents_client.py
mlclient/clients/eval_client.py
mlclient/clients/logs_client.py
mlclient/clients/ml_client.py
mlclient/constants.py
mlclient/exceptions.py
mlclient/jobs/__init__.py
mlclient/jobs/documents_jobs.py
mlclient/mimetypes.py
mlclient/ml_config.py
mlclient/ml_manager.py
mlclient/ml_response_parser.py
mlclient/model/__init__.py
mlclient/model/data.py
mlclient/resources/__init__.py
mlclient/resources/logging.yaml
mlclient/resources/mimetypes.yaml
mlclient/utils.py
mlclient-0.4.1.dist-info/LICENSE
mlclient-0.4.1.dist-info/METADATA
mlclient-0.4.1.dist-info/WHEEL
mlclient-0.4.1.dist-info/entry_points.txt
mlclient-0.4.1.dist-info/RECORD
