Metadata-Version: 2.1
Name: mlclient
Version: 0.4.1
Summary: A python client managing your MarkLogic instance
Home-page: https://github.com/monasticus/mlclient
License: MIT
Keywords: MarkLogic,marklogic,database,client,data,xml,json,NoSQL,nosql
Author: Tomasz Aniołowski
Author-email: tomasz.maciej.aniolowski@gmail.com
Requires-Python: >=3.8,<4.0
Classifier: Development Status :: 3 - Alpha
Classifier: Environment :: Console
Classifier: Intended Audience :: Developers
Classifier: License :: OSI Approved :: MIT License
Classifier: Programming Language :: Python
Classifier: Programming Language :: Python :: 3
Classifier: Programming Language :: Python :: 3.8
Classifier: Programming Language :: Python :: 3.9
Classifier: Programming Language :: Python :: 3.10
Classifier: Programming Language :: Python :: 3.11
Classifier: Programming Language :: Python :: 3.12
Classifier: Programming Language :: Python :: 3 :: Only
Classifier: Topic :: Database
Classifier: Topic :: Database :: Database Engines/Servers
Classifier: Topic :: Software Development
Classifier: Topic :: Software Development :: Libraries
Classifier: Topic :: Software Development :: Libraries :: Python Modules
Classifier: Topic :: Utilities
Requires-Dist: cleo (>=2.0.1,<3.0.0)
Requires-Dist: pydantic (>=2.5.2,<3.0.0)
Requires-Dist: python-dateutil (>=2.8.2,<3.0.0)
Requires-Dist: pyyaml (>=6.0.1,<7.0.0)
Requires-Dist: requests (>=2.31.0,<3.0.0)
Requires-Dist: requests-toolbelt (>=1.0.0,<2.0.0)
Requires-Dist: urllib3 (>=2.1.0,<3.0.0)
Requires-Dist: xmltodict (>=0.13.0,<0.14.0)
Project-URL: Documentation, https://mlclient.readthedocs.io/en/0.4.1
Project-URL: Repository, https://github.com/monasticus/mlclient
